blackmesa_dbt/__init__.py
blackmesa_dbt/dbt_project.yml
blackmesa_dbt/main.py
blackmesa_dbt/profiles.yml
blackmesa_dbt/models/README.md
blackmesa_dbt/models/staging/blackmesa/_blackmesa__models.yml
blackmesa_dbt/models/staging/blackmesa/stg_blackmesa__identities.sql
blackmesa_dbt/seeds/README.md
blackmesa_dbt-0.1.1.dist-info/METADATA
blackmesa_dbt-0.1.1.dist-info/WHEEL
blackmesa_dbt-0.1.1.dist-info/entry_points.txt
blackmesa_dbt-0.1.1.dist-info/top_level.txt
blackmesa_dbt-0.1.1.dist-info/RECORD
